zdm/__init__.py
zdm/logging.py
zdm/device/__init__.py
zdm/device/constants.py
zdm/device/credentials.py
zdm/device/mqtt.py
zdm/device/zdmclient.py
zdm_client_py-1.0.1.dist-info/METADATA
zdm_client_py-1.0.1.dist-info/WHEEL
zdm_client_py-1.0.1.dist-info/top_level.txt
zdm_client_py-1.0.1.dist-info/RECORD
