Metadata-Version: 2.1
Name: zdm-client-py
Version: 1.0.1
Summary: ZDM Client Python Library
Home-page: https://github.com/zerynth/zdm-client-py.git
Author: Zerynth Team
Author-email: d.neri@zerynth.com
License: UNKNOWN
Platform: UNKNOWN
Classifier: Programming Language :: Python :: 3
Classifier: License :: OSI Approved :: MIT License
Classifier: Operating System :: OS Independent
Requires-Python: >=3
Requires-Dist: paho-mqtt
Requires-Dist: click
Requires-Dist: pyjwt
